diapysef/__init__.py
diapysef/conversions.py
diapysef/convert_tdf_to_mzml.py
diapysef/coverage.py
diapysef/diapysef.py
diapysef/main.py
diapysef/merge_consumer.py
diapysef/pasefdata.py
diapysef/plotting.py
diapysef/proto_two_dimension_gradient_ascent_peak_finding.py
diapysef/splitting_consumer.py
diapysef/targeted_data_extraction.py
diapysef/timsdata.py
diapysef/two_dimension_gradient_ascent_peak_finder.py
diapysef/two_dimension_gradient_ascent_peak_finding.py
diapysef/two_dimension_quantification.py
diapysef/util.py
diapysef/data/evidence_example.pickle
diapysef-1.0.1.data/scripts/annotate_mq_ionmobility.py
diapysef-1.0.1.data/scripts/convertTDFtoMzML.py
diapysef-1.0.1.data/scripts/create_library.py
diapysef-1.0.1.data/scripts/get_dia_windows.py
diapysef-1.0.1.data/scripts/high_precision_irt.py
diapysef-1.0.1.data/scripts/plot_dia_windows.py
diapysef-1.0.1.dist-info/METADATA
diapysef-1.0.1.dist-info/WHEEL
diapysef-1.0.1.dist-info/entry_points.txt
diapysef-1.0.1.dist-info/top_level.txt
diapysef-1.0.1.dist-info/RECORD
