Metadata-Version: 2.1
Name: diapysef
Version: 1.0.1
Summary: Analysis, conversion and visualization of diaPASEF data.
Home-page: https://github.com/Roestlab/dia-pasef
Author: Max Frank, Annie Ha, Hannes Roest
Author-email: hannes.rost@utoronto.ca
License: MIT
Platform: UNKNOWN
Requires-Dist: pandas
Requires-Dist: numpy
Requires-Dist: matplotlib
Requires-Dist: statsmodels
Requires-Dist: pyopenms
Requires-Dist: patsy
Requires-Dist: tqdm
Requires-Dist: joblib
Requires-Dist: click
